[
  {
    "title": "Мать",
    "description": "[{\"region\":\"Самарканд\",\"word\":\"Мать\"},{\"region\":\"Сурхандарья\",\"word\":\"Мама\"},{\"region\":\"Бухара\",\"word\":\"Мать\"},{\"region\":\"Андижан\",\"word\":\"Мать\"},{\"region\":\"Хорезм\",\"word\":\"Мама\"},{\"region\":\"Ташкент\",\"word\":\"Мать\"},{\"region\":\"Наманган\",\"word\":\"Мать\"},{\"region\":\"Фергана\",\"word\":\"Мать\"},{\"region\":\"Кашкадарья\",\"word\":\"Мать\"},{\"region\":\"Джизак\",\"word\":\"Мать\"}]"
  },
  {
    "title": "Сестра",
    "description": "[{\"region\":\"Самарканд\",\"word\":\"Сестра\"},{\"region\":\"Сурхандарья\",\"word\":\"Сестрёнка\"},{\"region\":\"Бухара\",\"word\":\"Сестра\"},{\"region\":\"Андижан\",\"word\":\"Сестра\"},{\"region\":\"Хорезм\",\"word\":\"Сестрица\"},{\"region\":\"Ташкент\",\"word\":\"Сестра\"},{\"region\":\"Наманган\",\"word\":\"Сестра\"},{\"region\":\"Фергана\",\"word\":\"Сестра\"},{\"region\":\"Кашкадарья\",\"word\":\"Сестра\"},{\"region\":\"Джизак\",\"word\":\"Сестра\"}]"
  },
  {
    "title": "Хлеб",
    "description": "[{\"region\":\"Самарканд\",\"word\":\"Хлеб\"},{\"region\":\"Сурхандарья\",\"word\":\"Буханка\"},{\"region\":\"Бухара\",\"word\":\"Хлеб\"},{\"region\":\"Андижан\",\"word\":\"Хлеб\"},{\"region\":\"Хорезм\",\"word\":\"Нан\"},{\"region\":\"Ташкент\",\"word\":\"Хлеб\"},{\"region\":\"Наманган\",\"word\":\"Хлеб\"},{\"region\":\"Фергана\",\"word\":\"Хлеб\"},{\"region\":\"Кашкадарья\",\"word\":\"Хлеб\"},{\"region\":\"Джизак\",\"word\":\"Хлеб\"}]"
  },
  {
    "title": "Вода",
    "description": "[{\"region\":\"Самарканд\",\"word\":\"Вода\"},{\"region\":\"Сурхандарья\",\"word\":\"Об\"},{\"region\":\"Бухара\",\"word\":\"Об\"},{\"region\":\"Андижан\",\"word\":\"Вода\"},{\"region\":\"Хорезм\",\"word\":\"Сув\"},{\"region\":\"Ташкент\",\"word\":\"Вода\"},{\"region\":\"Наманган\",\"word\":\"Вода\"},{\"region\":\"Фергана\",\"word\":\"Вода\"},{\"region\":\"Кашкадарья\",\"word\":\"Вода\"},{\"region\":\"Джизак\",\"word\":\"Вода\"}]"
  },
  {
    "title": "Ребёнок",
    "description": "[{\"region\":\"Самарканд\",\"word\":\"Ребёнок\"},{\"region\":\"Сурхандарья\",\"word\":\"Малыш\"},{\"region\":\"Бухара\",\"word\":\"Сын\"},{\"region\":\"Андижан\",\"word\":\"Ребёнок\"},{\"region\":\"Хорезм\",\"word\":\"Мальчик\"},{\"region\":\"Ташкент\",\"word\":\"Ребёнок\"},{\"region\":\"Наманган\",\"word\":\"Ребёнок\"},{\"region\":\"Фергана\",\"word\":\"Ребёнок\"},{\"region\":\"Кашкадарья\",\"word\":\"Ребёнок\"},{\"region\":\"Джизак\",\"word\":\"Ребёнок\"}]"
  },
  {
    "title": "Девочка",
    "description": "[{\"region\":\"Самарканд\",\"word\":\"Девочка\"},{\"region\":\"Сурхандарья\",\"word\":\"Маленькая девочка\"},{\"region\":\"Бухара\",\"word\":\"Дочь\"},{\"region\":\"Андижан\",\"word\":\"Девочка\"},{\"region\":\"Хорезм\",\"word\":\"Девочка\"},{\"region\":\"Ташкент\",\"word\":\"Девочка\"},{\"region\":\"Наманган\",\"word\":\"Девочка\"},{\"region\":\"Фергана\",\"word\":\"Девочка\"},{\"region\":\"Кашкадарья\",\"word\":\"Девочка\"},{\"region\":\"Джизак\",\"word\":\"Девочка\"}]"
  },
  {
    "title": "Мальчик",
    "description": "[{\"region\":\"Самарканд\",\"word\":\"Мальчик\"},{\"region\":\"Сурхандарья\",\"word\":\"Парень\"},{\"region\":\"Бухара\",\"word\":\"Мальчик\"},{\"region\":\"Андижан\",\"word\":\"Мальчик\"},{\"region\":\"Хорезм\",\"word\":\"Юноша\"},{\"region\":\"Ташкент\",\"word\":\"Мальчик\"},{\"region\":\"Наманган\",\"word\":\"Парень\"},{\"region\":\"Фергана\",\"word\":\"Мальчик\"},{\"region\":\"Кашкадарья\",\"word\":\"Мальчик\"},{\"region\":\"Джизак\",\"word\":\"Мальчик\"}]"
  },
  {
    "title": "Здравствуйте",
    "description": "[{\"region\":\"Самарканд\",\"word\":\"Здравствуйте\"},{\"region\":\"Сурхандарья\",\"word\":\"Салам\"},{\"region\":\"Бухара\",\"word\":\"Здравствуйте\"},{\"region\":\"Андижан\",\"word\":\"Здравствуйте\"},{\"region\":\"Хорезм\",\"word\":\"Привет\"},{\"region\":\"Ташкент\",\"word\":\"Здравствуйте\"},{\"region\":\"Наманган\",\"word\":\"Здравствуйте\"},{\"region\":\"Фергана\",\"word\":\"Здравствуйте\"},{\"region\":\"Кашкадарья\",\"word\":\"Здравствуйте\"},{\"region\":\"Джизак\",\"word\":\"Здравствуйте\"}]"
  },
  {
    "title": "Книга",
    "description": "[{\"region\":\"Самарканд\",\"word\":\"Книга\"},{\"region\":\"Сурхандарья\",\"word\":\"Книга\"},{\"region\":\"Бухара\",\"word\":\"Книга\"},{\"region\":\"Андижан\",\"word\":\"Книга\"},{\"region\":\"Хорезм\",\"word\":\"Книга\"},{\"region\":\"Ташкент\",\"word\":\"Книга\"},{\"region\":\"Наманган\",\"word\":\"Книга\"},{\"region\":\"Фергана\",\"word\":\"Книга\"},{\"region\":\"Кашкадарья\",\"word\":\"Книга\"},{\"region\":\"Джизак\",\"word\":\"Книга\"}]"
  },
  {
    "title": "Школа",
    "description": "[{\"region\":\"Самарканд\",\"word\":\"Школа\"},{\"region\":\"Сурхандарья\",\"word\":\"Школа\"},{\"region\":\"Бухара\",\"word\":\"Школа\"},{\"region\":\"Андижан\",\"word\":\"Школа\"},{\"region\":\"Хорезм\",\"word\":\"Школа\"},{\"region\":\"Ташкент\",\"word\":\"Школа\"},{\"region\":\"Наманган\",\"word\":\"Школа\"},{\"region\":\"Фергана\",\"word\":\"Школа\"},{\"region\":\"Кашкадарья\",\"word\":\"Школа\"},{\"region\":\"Джизак\",\"word\":\"Школа\"}]"
  },
  {
    "title": "Дом",
    "description": "[{\"region\":\"Самарканд\",\"word\":\"Дом\"},{\"region\":\"Сурхандарья\",\"word\":\"Дом\"},{\"region\":\"Бухара\",\"word\":\"Дом\"},{\"region\":\"Андижан\",\"word\":\"Дом\"},{\"region\":\"Хорезм\",\"word\":\"Дом\"},{\"region\":\"Ташкент\",\"word\":\"Дом\"},{\"region\":\"Наманган\",\"word\":\"Дом\"},{\"region\":\"Фергана\",\"word\":\"Дом\"},{\"region\":\"Кашкадарья\",\"word\":\"Дом\"},{\"region\":\"Джизак\",\"word\":\"Дом\"}]"
  },
  {
    "title": "Машина",
    "description": "[{\"region\":\"Самарканд\",\"word\":\"Машина\"},{\"region\":\"Сурхандарья\",\"word\":\"Машина\"},{\"region\":\"Бухара\",\"word\":\"Машина\"},{\"region\":\"Андижан\",\"word\":\"Машина\"},{\"region\":\"Хорезм\",\"word\":\"Машина\"},{\"region\":\"Ташкент\",\"word\":\"Машина\"},{\"region\":\"Наманган\",\"word\":\"Машина\"},{\"region\":\"Фергана\",\"word\":\"Машина\"},{\"region\":\"Кашкадарья\",\"word\":\"Машина\"},{\"region\":\"Джизак\",\"word\":\"Машина\"}]"
  },
  {
    "title": "Друг",
    "description": "[{\"region\":\"Самарканд\",\"word\":\"Друг\"},{\"region\":\"Сурхандарья\",\"word\":\"Друг\"},{\"region\":\"Бухара\",\"word\":\"Друг\"},{\"region\":\"Андижан\",\"word\":\"Друг\"},{\"region\":\"Хорезм\",\"word\":\"Друг\"},{\"region\":\"Ташкент\",\"word\":\"Друг\"},{\"region\":\"Наманган\",\"word\":\"Друг\"},{\"region\":\"Фергана\",\"word\":\"Друг\"},{\"region\":\"Кашкадарья\",\"word\":\"Друг\"},{\"region\":\"Джизак\",\"word\":\"Друг\"}]"
  },
  {
    "title": "Чай",
    "description": "[{\"region\":\"Самарканд\",\"word\":\"Чай\"},{\"region\":\"Сурхандарья\",\"word\":\"Чай\"},{\"region\":\"Бухара\",\"word\":\"Чай\"},{\"region\":\"Андижан\",\"word\":\"Чай\"},{\"region\":\"Хорезм\",\"word\":\"Чай\"},{\"region\":\"Ташкент\",\"word\":\"Чай\"},{\"region\":\"Наманган\",\"word\":\"Чай\"},{\"region\":\"Фергана\",\"word\":\"Чай\"},{\"region\":\"Кашкадарья\",\"word\":\"Чай\"},{\"region\":\"Джизак\",\"word\":\"Чай\"}]"
  },
  {
    "title": "Камень",
    "description": "[{\"region\":\"Самарканд\",\"word\":\"Камень\"},{\"region\":\"Сурхандарья\",\"word\":\"Камень\"},{\"region\":\"Бухара\",\"word\":\"Камень\"},{\"region\":\"Андижан\",\"word\":\"Камень\"},{\"region\":\"Хорезм\",\"word\":\"Камень\"},{\"region\":\"Ташкент\",\"word\":\"Камень\"},{\"region\":\"Наманган\",\"word\":\"Камень\"},{\"region\":\"Фергана\",\"word\":\"Камень\"},{\"region\":\"Кашкадарья\",\"word\":\"Камень\"},{\"region\":\"Джизак\",\"word\":\"Камень\"}]"
  },
  {
    "title": "Возлюбленный",
    "description": "[{\"region\":\"Самарканд\",\"word\":\"Возлюбленный\"},{\"region\":\"Сурхандарья\",\"word\":\"Возлюбленный\"},{\"region\":\"Бухара\",\"word\":\"Возлюбленный\"},{\"region\":\"Андижан\",\"word\":\"Возлюбленный\"},{\"region\":\"Хорезм\",\"word\":\"Возлюбленный\"},{\"region\":\"Ташкент\",\"word\":\"Возлюбленный\"},{\"region\":\"Наманган\",\"word\":\"Возлюбленный\"},{\"region\":\"Фергана\",\"word\":\"Возлюбленный\"},{\"region\":\"Кашкадарья\",\"word\":\"Возлюбленный\"},{\"region\":\"Джизак\",\"word\":\"Возлюбленный\"}]"
  },
  {
    "title": "Сад",
    "description": "[{\"region\":\"Самарканд\",\"word\":\"Сад\"},{\"region\":\"Сурхандарья\",\"word\":\"Сад\"},{\"region\":\"Бухара\",\"word\":\"Сад\"},{\"region\":\"Андижан\",\"word\":\"Сад\"},{\"region\":\"Хорезм\",\"word\":\"Сад\"},{\"region\":\"Ташкент\",\"word\":\"Сад\"},{\"region\":\"Наманган\",\"word\":\"Сад\"},{\"region\":\"Фергана\",\"word\":\"Сад\"},{\"region\":\"Кашкадарья\",\"word\":\"Сад\"},{\"region\":\"Джизак\",\"word\":\"Сад\"}]"
  },
  {
    "title": "Зеркало",
    "description": "[{\"region\":\"Самарканд\",\"word\":\"Зеркало\"},{\"region\":\"Сурхандарья\",\"word\":\"Зеркало\"},{\"region\":\"Бухара\",\"word\":\"Зеркало\"},{\"region\":\"Андижан\",\"word\":\"Зеркало\"},{\"region\":\"Хорезм\",\"word\":\"Зеркало\"},{\"region\":\"Ташкент\",\"word\":\"Зеркало\"},{\"region\":\"Наманган\",\"word\":\"Зеркало\"},{\"region\":\"Фергана\",\"word\":\"Зеркало\"},{\"region\":\"Кашкадарья\",\"word\":\"Зеркало\"},{\"region\":\"Джизак\",\"word\":\"Зеркало\"}]"
  }
]
